django_candy/__init__.py
django_candy/admin.py
django_candy/apps.py
django_candy/middleware.py
django_candy/models.py
django_candy/serializers.py
django_candy/tests.py
django_candy/urls.py
django_candy/utils.py
django_candy/views.py
django_candy/migrations/__init__.py
django_candy-0.7.2.dist-info/LICENSE.txt
django_candy-0.7.2.dist-info/METADATA
django_candy-0.7.2.dist-info/WHEEL
django_candy-0.7.2.dist-info/top_level.txt
django_candy-0.7.2.dist-info/RECORD
